pymelodia/__init__.py
pymelodia/config.py
pymelodia/api/__init__.py
pymelodia/api/crypto_helper.py
pymelodia/api/netease_api.py
pymelodia/cli/__init__.py
pymelodia/cli/command_line.py
pymelodia/core/crypto_helper.py
pymelodia/core/music_api.py
pymelodia/core/threading_manager.py
pymelodia/processors/__init__.py
pymelodia/processors/file_processor.py
pymelodia/services/__init__.py
pymelodia/services/download_service.py
pymelodia/storage/__init__.py
pymelodia/storage/database.py
pymelodia/ui/progress_display.py
pymelodia/utils/logger.py
pymelodia-1.1.3.dist-info/licenses/LICENSE
pymelodia-1.1.3.dist-info/METADATA
pymelodia-1.1.3.dist-info/WHEEL
pymelodia-1.1.3.dist-info/entry_points.txt
pymelodia-1.1.3.dist-info/top_level.txt
pymelodia-1.1.3.dist-info/RECORD
