Metadata-Version: 2.4
Name: pymelodia
Version: 1.1.3
Summary: 🎵 网易云音乐下载工具
Home-page: https://github.com/yht0511/melodia
Author: yht0511
Author-email: yht0511 <admin@teclab.org.cn>
License: MIT
Project-URL: Homepage, https://github.com/yht0511/melodia
Project-URL: Bug Reports, https://github.com/yht0511/melodia/issues
Project-URL: Source, https://github.com/yht0511/melodia
Project-URL: Documentation, https://github.com/yht0511/melodia/blob/main/README.md
Keywords: music,download,netease,网易云,音乐下载,命令行工具
Classifier: Development Status :: 4 - Beta
Classifier: Intended Audience :: End Users/Desktop
Classifier: Topic :: Multimedia :: Sound/Audio
Classifier: Topic :: Internet :: WWW/HTTP
Classifier: License :: OSI Approved :: MIT License
Classifier: Programming Language :: Python :: 3
Classifier: Programming Language :: Python :: 3.7
Classifier: Programming Language :: Python :: 3.8
Classifier: Programming Language :: Python :: 3.9
Classifier: Programming Language :: Python :: 3.10
Classifier: Programming Language :: Python :: 3.11
Classifier: Operating System :: OS Independent
Classifier: Environment :: Console
Requires-Python: >=3.7
License-File: LICENSE
Requires-Dist: requests>=2.28.0
Requires-Dist: beautifulsoup4>=4.11.0
Requires-Dist: lxml>=4.9.0
Requires-Dist: eyed3>=0.9.6
Requires-Dist: pycryptodome>=3.17.0
Requires-Dist: PyExecJS>=1.5.1
Dynamic: author
Dynamic: home-page
Dynamic: license-file
Dynamic: requires-python
